[
  {
    "location": "010__Daniel_Otykier\\Tabular",
    "version": "2.16.6",
    "zipUrl": "https://github.com/TabularEditor/TabularEditor/releases/download/2.16.6/TabularEditor.Portable.zip"
  },
  {
    "location": "010__Daniel_Otykier\\TabularV3",
    "version": "3.2.3",
    "zipUrl": "https://cdn.tabulareditor.com/files/TabularEditor.3.2.3.x64.zip"
  },
  {
    "location": "020__Michael_Kovalsky\\ReportAnalyzer",
    "version": "1.6.0",
    "zipUrl": "https://github.com/m-kovalsky/ReportAnalyzer/releases/download/1.6.0/ReportAnalyzer.Portable.zip"
  }
]
